add.py
add_15_05_23-0.1.0.dist-info/LICENSE.txt
add_15_05_23-0.1.0.dist-info/METADATA
add_15_05_23-0.1.0.dist-info/WHEEL
add_15_05_23-0.1.0.dist-info/top_level.txt
add_15_05_23-0.1.0.dist-info/RECORD
